kicad_symlib_utility/__init__.py
kicad_symlib_utility/symbol_file_class.py
kicad_symlib_utility-1.0.0.dist-info/licenses/LICENSE
kicad_symlib_utility-1.0.0.dist-info/METADATA
kicad_symlib_utility-1.0.0.dist-info/WHEEL
kicad_symlib_utility-1.0.0.dist-info/top_level.txt
kicad_symlib_utility-1.0.0.dist-info/RECORD
