Metadata-Version: 2.4
Name: kicad-symlib-utility
Version: 1.0.0
Summary: A package to process KiCad symbol libraries
Author: dbwalker0min
License-Expression: MIT
Keywords: kicad,symbol,library,electronics,schematic
Classifier: Development Status :: 4 - Beta
Classifier: Intended Audience :: Developers
Classifier: Programming Language :: Python :: 3
Classifier: Programming Language :: Python :: 3.12
Classifier: Topic :: Software Development :: Libraries :: Python Modules
Classifier: Topic :: Scientific/Engineering :: Electronic Design Automation (EDA)
Requires-Python: >=3.12
License-File: LICENSE
Requires-Dist: sexpdata>=1.0.2
Dynamic: license-file
